[
  {
    "rank": 1,
    "name": "オリックス",
    "playGameCount": 106,
    "win": 51,
    "lose": 41,
    "draw": 14,
    "pct": 0.554,
    "gameDiff": "-",
    "remainingMatch": 37,
    "run": 426,
    "ra": 400,
    "hr": 98,
    "sb": 33,
    "avg": 0.253,
    "era": 3.57,
    "pythagoreanExpectation": 0.531
  },
  {
    "rank": 2,
    "name": "ロッテ",
    "playGameCount": 103,
    "win": 48,
    "lose": 40,
    "draw": 15,
    "pct": 0.545,
    "gameDiff": "1",
    "remainingMatch": 40,
    "run": 465,
    "ra": 429,
    "hr": 97,
    "sb": 90,
    "avg": 0.253,
    "era": 3.92,
    "pythagoreanExpectation": 0.54
  },
  {
    "rank": 3,
    "name": "楽天",
    "playGameCount": 106,
    "win": 48,
    "lose": 45,
    "draw": 13,
    "pct": 0.516,
    "gameDiff": "2.5",
    "remainingMatch": 37,
    "run": 406,
    "ra": 400,
    "hr": 81,
    "sb": 38,
    "avg": 0.246,
    "era": 3.62,
    "pythagoreanExpectation": 0.507
  },
  {
    "rank": 4,
    "name": "ソフトバンク",
    "playGameCount": 107,
    "win": 45,
    "lose": 45,
    "draw": 17,
    "pct": 0.5,
    "gameDiff": "1.5",
    "remainingMatch": 36,
    "run": 426,
    "ra": 358,
    "hr": 93,
    "sb": 63,
    "avg": 0.248,
    "era": 3.23,
    "pythagoreanExpectation": 0.586
  },
  {
    "rank": 5,
    "name": "西武",
    "playGameCount": 106,
    "win": 40,
    "lose": 49,
    "draw": 17,
    "pct": 0.449,
    "gameDiff": "4.5",
    "remainingMatch": 37,
    "run": 416,
    "ra": 455,
    "hr": 87,
    "sb": 73,
    "avg": 0.248,
    "era": 4.09,
    "pythagoreanExpectation": 0.455
  },
  {
    "rank": 6,
    "name": "日本ハム",
    "playGameCount": 100,
    "win": 36,
    "lose": 49,
    "draw": 15,
    "pct": 0.424,
    "gameDiff": "2",
    "remainingMatch": 43,
    "run": 321,
    "ra": 386,
    "hr": 55,
    "sb": 56,
    "avg": 0.234,
    "era": 3.52,
    "pythagoreanExpectation": 0.409
  }
]